vm2ami/__init__.py
vm2ami/vm2ami.py
vm2ami-1.0.0.data/scripts/vm2ami
vm2ami-1.0.0.dist-info/DESCRIPTION.rst
vm2ami-1.0.0.dist-info/METADATA
vm2ami-1.0.0.dist-info/RECORD
vm2ami-1.0.0.dist-info/WHEEL
vm2ami-1.0.0.dist-info/metadata.json
vm2ami-1.0.0.dist-info/top_level.txt
